LICENSE
outlookcalendarsyncer/__init__.py
outlookcalendarsyncer/application.py
outlookcalendarsyncer/configuration.py
outlookcalendarsyncer/loggingutils.py
outlookcalendarsyncer/outlook.py
outlookcalendarsyncer/synchronizer.py
outlookcalendarsyncer-0.1.0.dist-info/entry_points.txt
outlookcalendarsyncer-0.1.0.dist-info/LICENSE
outlookcalendarsyncer-0.1.0.dist-info/WHEEL
outlookcalendarsyncer-0.1.0.dist-info/METADATA
outlookcalendarsyncer-0.1.0.dist-info/RECORD
