Metadata-Version: 2.1
Name: outlookcalendarsyncer
Version: 0.1.0
Summary: 
Home-page: https://github.com/MattiooFR/package_name
License: MIT
Author: Alnen
Author-email: uzhegov37@yahoo.com
Requires-Python: >=3.9,<4.0
Classifier: License :: OSI Approved :: MIT License
Classifier: Programming Language :: Python :: 3
Classifier: Programming Language :: Python :: 3.9
Requires-Dist: O365 (>=2.0.15,<3.0.0)
Requires-Dist: dataclasses-json (>=0.5.5,<0.6.0)
Requires-Dist: tzlocal (==2.1)
Project-URL: Repository, https://github.com/Alnen/OutlookCalendarSyncer
